taskblaster/__init__.py
taskblaster/__main__.py
taskblaster/abc.py
taskblaster/cache.py
taskblaster/clobber.py
taskblaster/conflict.py
taskblaster/encodedtask.py
taskblaster/encoding.py
taskblaster/entry.py
taskblaster/errorhandlers.py
taskblaster/future.py
taskblaster/heuristics.py
taskblaster/labeltable.py
taskblaster/listing.py
taskblaster/mqintegration.py
taskblaster/namedtask.py
taskblaster/parallel.py
taskblaster/records.py
taskblaster/registry.py
taskblaster/repository.py
taskblaster/runner.py
taskblaster/sphinxblaster.py
taskblaster/state.py
taskblaster/storage.py
taskblaster/tablemapping.py
taskblaster/testing.py
taskblaster/tree.py
taskblaster/util.py
taskblaster/view.py
taskblaster/view_workflow.py
taskblaster/view_workflow_html.py
taskblaster/worker.py
taskblaster/workers.py
taskblaster/workflowtable.py
taskblaster/cli/__init__.py
taskblaster/cli/main.py
taskblaster/cli/registry.py
taskblaster/cli/special.py
taskblaster/cli/tags.py
taskblaster/cli/warden.py
taskblaster/cli/workers.py
taskblaster-0.2.dist-info/COPYING
taskblaster-0.2.dist-info/LICENSE
taskblaster-0.2.dist-info/METADATA
taskblaster-0.2.dist-info/WHEEL
taskblaster-0.2.dist-info/entry_points.txt
taskblaster-0.2.dist-info/top_level.txt
taskblaster-0.2.dist-info/RECORD
