Metadata-Version: 2.2
Name: taskblaster
Version: 0.2
Summary: Light-weight computational workflow manager
Project-URL: documentation, https://taskblaster.readthedocs.io/
Project-URL: repository, https://gitlab.com/taskblaster/taskblaster.git
Project-URL: issues, https://gitlab.com/taskblaster/taskblaster/issues
Classifier: License :: OSI Approved :: GNU General Public License v3 or later (GPLv3+)
Classifier: Environment :: Console
Requires-Python: >=3.9
License-File: LICENSE
License-File: COPYING
Requires-Dist: click>=8.0.0
Provides-Extra: doc
Requires-Dist: sphinx; extra == "doc"
Requires-Dist: sphinx_rtd_theme; extra == "doc"
Requires-Dist: sphinx_click; extra == "doc"
Provides-Extra: dev
Requires-Dist: pytest; extra == "dev"
